distance_explainer.py
distance_explainer-0.4.0.dist-info/LICENSE
distance_explainer-0.4.0.dist-info/METADATA
distance_explainer-0.4.0.dist-info/WHEEL
distance_explainer-0.4.0.dist-info/top_level.txt
distance_explainer-0.4.0.dist-info/RECORD
