Metadata-Version: 2.1
Name: distance_explainer
Version: 0.4.0
Summary: XAI method to explain distances in embedded spaces
Home-page: https://github.com/dianna-ai/distance_explainer
Author: Christiaan Meijer
Author-email: c.meijer@esciencecenter.nl
Project-URL: Bug Tracker, https://github.com/dianna-ai/distance_explainer/issues
Keywords: XAI,embedded spaces
Classifier: Development Status :: 2 - Pre-Alpha
Classifier: Intended Audience :: Developers
Classifier: License :: OSI Approved :: Apache Software License
Classifier: Natural Language :: English
Classifier: Programming Language :: Python :: 3
Classifier: Programming Language :: Python :: 3.9
Classifier: Programming Language :: Python :: 3.10
Classifier: Programming Language :: Python :: 3.11
Classifier: Programming Language :: Python :: 3.12
Requires-Python: >=3.9
License-File: LICENSE
Requires-Dist: dianna>=1.4
Requires-Dist: numpy
Requires-Dist: pytest
Requires-Dist: tqdm
Requires-Dist: scikit-learn
Requires-Dist: pyyaml
Requires-Dist: dataclass-wizard
Provides-Extra: dev
Requires-Dist: build; extra == "dev"
Requires-Dist: bump2version; extra == "dev"
Requires-Dist: coverage[toml]; extra == "dev"
Requires-Dist: ruff; extra == "dev"
Requires-Dist: pytest; extra == "dev"
Requires-Dist: pytest-cov; extra == "dev"
Requires-Dist: sphinx; extra == "dev"
Requires-Dist: sphinx-rtd-theme; extra == "dev"
Requires-Dist: sphinx-autoapi; extra == "dev"
Requires-Dist: tox; extra == "dev"
Requires-Dist: myst-parser; extra == "dev"
Provides-Extra: publishing
Requires-Dist: twine; extra == "publishing"
Requires-Dist: wheel; extra == "publishing"
